[[{"__type__":"cc.Prefab","_name":"003","data":{"__id__":1}},{"__type__":"cc.Node","_name":"001","_children":[{"__id__":2},{"__id__":13}],"_prefab":{"__type__":"cc.PrefabInfo","root":{"__id__":1},"asset":{"__uuid__":"5162fj7ORDpqPurSN/cTlP"},"fileId":"209JFGS7ZALZ02WQ0n5NUV"},"_trs":{"__type__":"TypedArray","ctor":"Float64Array","array":[0,-30,0,0,0,0,1,1,1,1]}},{"__type__":"cc.Node","_name":"image_a","_parent":{"__id__":1},"_children":[{"__id__":3},{"__id__":5},{"__id__":7},{"__id__":9},{"__id__":11}],"_components":[{"__type__":"cc.Sprite","node":{"__id__":2},"_materials":[{"__uuid__":"ecpdLyjvZBwrvm+cedCcQy"}],"_spriteFrame":{"__uuid__":"9ckJ+0bvJIe7fXp28JUbpn"},"_sizeMode":0},{"__type__":"cc.Button","node":{"__id__":2},"_N$normalColor":{"__type__":"cc.Color","r":214,"g":214,"b":214}}],"_prefab":{"__type__":"cc.PrefabInfo","root":{"__id__":1},"asset":{"__uuid__":"5162fj7ORDpqPurSN/cTlP"},"fileId":"99BnVVt6tKKL5Lj8CJSgQV"},"_contentSize":{"__type__":"cc.Size","width":640,"height":480},"_trs":{"__type__":"TypedArray","ctor":"Float64Array","array":[0,244,0,0,0,0,1,1,1,1]}},{"__type__":"cc.Node","_name":"node","_parent":{"__id__":2},"_children":[{"__id__":4}],"_components":[{"__type__":"cc.Sprite","node":{"__id__":3},"_materials":[{"__uuid__":"ecpdLyjvZBwrvm+cedCcQy"}],"_spriteFrame":{"__uuid__":"75iGBJYUhLG6iBNkEpua6t"},"_sizeMode":2}],"_prefab":{"__type__":"cc.PrefabInfo","root":{"__id__":1},"asset":{"__uuid__":"5162fj7ORDpqPurSN/cTlP"},"fileId":"26gf2WDz9KBbiIUEcgm+vc"},"_contentSize":{"__type__":"cc.Size","width":92,"height":92},"_trs":{"__type__":"TypedArray","ctor":"Float64Array","array":[45.607,71.193,0,0,0,0,1,1,1,1]}},{"__type__":"cc.Node","_name":"btn","_parent":{"__id__":3},"_components":[{"__type__":"cc.Button","node":{"__id__":4},"_N$normalColor":{"__type__":"cc.Color","r":214,"g":214,"b":214}}],"_prefab":{"__type__":"cc.PrefabInfo","root":{"__id__":1},"asset":{"__uuid__":"5162fj7ORDpqPurSN/cTlP"},"fileId":"1cFIAja2lPya78cVZbNtkO"},"_contentSize":{"__type__":"cc.Size","width":92,"height":92},"_trs":{"__type__":"TypedArray","ctor":"Float64Array","array":[0,0,0,0,0,0,1,1.499,1.305,1.482]}},{"__type__":"cc.Node","_name":"node","_parent":{"__id__":2},"_children":[{"__id__":6}],"_components":[{"__type__":"cc.Sprite","node":{"__id__":5},"_materials":[{"__uuid__":"ecpdLyjvZBwrvm+cedCcQy"}],"_spriteFrame":{"__uuid__":"75iGBJYUhLG6iBNkEpua6t"},"_sizeMode":2}],"_prefab":{"__type__":"cc.PrefabInfo","root":{"__id__":1},"asset":{"__uuid__":"5162fj7ORDpqPurSN/cTlP"},"fileId":"bfKw4IGfhLMocqt24j2kqV"},"_contentSize":{"__type__":"cc.Size","width":92,"height":92},"_trs":{"__type__":"TypedArray","ctor":"Float64Array","array":[271.814,141.916,0,0,0,0,1,1,1,1]}},{"__type__":"cc.Node","_name":"btn","_parent":{"__id__":5},"_components":[{"__type__":"cc.Button","node":{"__id__":6},"_N$normalColor":{"__type__":"cc.Color","r":214,"g":214,"b":214}}],"_prefab":{"__type__":"cc.PrefabInfo","root":{"__id__":1},"asset":{"__uuid__":"5162fj7ORDpqPurSN/cTlP"},"fileId":"18UcDg1UNLDrNdEFUy/j8D"},"_contentSize":{"__type__":"cc.Size","width":92,"height":92},"_trs":{"__type__":"TypedArray","ctor":"Float64Array","array":[0,0,0,0,0,0,1,0.999,1.124,0.549]}},{"__type__":"cc.Node","_name":"node","_parent":{"__id__":2},"_children":[{"__id__":8}],"_components":[{"__type__":"cc.Sprite","node":{"__id__":7},"_materials":[{"__uuid__":"ecpdLyjvZBwrvm+cedCcQy"}],"_spriteFrame":{"__uuid__":"75iGBJYUhLG6iBNkEpua6t"},"_sizeMode":2}],"_prefab":{"__type__":"cc.PrefabInfo","root":{"__id__":1},"asset":{"__uuid__":"5162fj7ORDpqPurSN/cTlP"},"fileId":"267EAh/phBNJqgpse8DFFz"},"_contentSize":{"__type__":"cc.Size","width":92,"height":92},"_trs":{"__type__":"TypedArray","ctor":"Float64Array","array":[-23.165,-176.869,0,0,0,0,1,1,1,1]}},{"__type__":"cc.Node","_name":"btn","_parent":{"__id__":7},"_components":[{"__type__":"cc.Button","node":{"__id__":8},"_N$normalColor":{"__type__":"cc.Color","r":214,"g":214,"b":214}}],"_prefab":{"__type__":"cc.PrefabInfo","root":{"__id__":1},"asset":{"__uuid__":"5162fj7ORDpqPurSN/cTlP"},"fileId":"8aYZ69I9JBLJjs9JiT886x"},"_contentSize":{"__type__":"cc.Size","width":92,"height":92},"_trs":{"__type__":"TypedArray","ctor":"Float64Array","array":[0,0,0,0,0,0,1,2.074,1.027,1.269]}},{"__type__":"cc.Node","_name":"node","_parent":{"__id__":2},"_children":[{"__id__":10}],"_components":[{"__type__":"cc.Sprite","node":{"__id__":9},"_materials":[{"__uuid__":"ecpdLyjvZBwrvm+cedCcQy"}],"_spriteFrame":{"__uuid__":"75iGBJYUhLG6iBNkEpua6t"},"_sizeMode":2}],"_prefab":{"__type__":"cc.PrefabInfo","root":{"__id__":1},"asset":{"__uuid__":"5162fj7ORDpqPurSN/cTlP"},"fileId":"63eRQKbYtLh7LhXPqVkSCw"},"_contentSize":{"__type__":"cc.Size","width":92,"height":92},"_trs":{"__type__":"TypedArray","ctor":"Float64Array","array":[-252.865,91.412,0,0,0,0,1,1,1,1]}},{"__type__":"cc.Node","_name":"btn","_parent":{"__id__":9},"_components":[{"__type__":"cc.Button","node":{"__id__":10},"_N$normalColor":{"__type__":"cc.Color","r":214,"g":214,"b":214}}],"_prefab":{"__type__":"cc.PrefabInfo","root":{"__id__":1},"asset":{"__uuid__":"5162fj7ORDpqPurSN/cTlP"},"fileId":"0fPMYLJKNF8pE98VnGhW7M"},"_contentSize":{"__type__":"cc.Size","width":92,"height":92},"_trs":{"__type__":"TypedArray","ctor":"Float64Array","array":[0,0,0,0,0,0,1,1.235,1.583,1.998]}},{"__type__":"cc.Node","_name":"node","_parent":{"__id__":2},"_children":[{"__id__":12}],"_components":[{"__type__":"cc.Sprite","node":{"__id__":11},"_materials":[{"__uuid__":"ecpdLyjvZBwrvm+cedCcQy"}],"_spriteFrame":{"__uuid__":"75iGBJYUhLG6iBNkEpua6t"},"_sizeMode":2}],"_prefab":{"__type__":"cc.PrefabInfo","root":{"__id__":1},"asset":{"__uuid__":"5162fj7ORDpqPurSN/cTlP"},"fileId":"a1aNkFaddBrJGEXvbO36ir"},"_contentSize":{"__type__":"cc.Size","width":92,"height":92},"_trs":{"__type__":"TypedArray","ctor":"Float64Array","array":[216.66,47.754,0,0,0,0,1,1.016,1.016,1.016]}},{"__type__":"cc.Node","_name":"btn","_parent":{"__id__":11},"_components":[{"__type__":"cc.Button","node":{"__id__":12},"_N$normalColor":{"__type__":"cc.Color","r":214,"g":214,"b":214}}],"_prefab":{"__type__":"cc.PrefabInfo","root":{"__id__":1},"asset":{"__uuid__":"5162fj7ORDpqPurSN/cTlP"},"fileId":"aadq1kz8pB2YIqu/fMw4ai"},"_contentSize":{"__type__":"cc.Size","width":92,"height":92},"_trs":{"__type__":"TypedArray","ctor":"Float64Array","array":[0,0,0,0,0,0,1,1.138,1.108,2.318]}},{"__type__":"cc.Node","_name":"image_b","_parent":{"__id__":1},"_components":[{"__type__":"cc.Sprite","node":{"__id__":13},"_materials":[{"__uuid__":"ecpdLyjvZBwrvm+cedCcQy"}],"_spriteFrame":{"__uuid__":"dfSTFZoU5N2LHITh+zniLW"},"_sizeMode":0},{"__type__":"cc.Button","node":{"__id__":13},"_N$normalColor":{"__type__":"cc.Color","r":214,"g":214,"b":214}}],"_prefab":{"__type__":"cc.PrefabInfo","root":{"__id__":1},"asset":{"__uuid__":"5162fj7ORDpqPurSN/cTlP"},"fileId":"ebu11xMGBMfpIRIsj+gkoO"},"_contentSize":{"__type__":"cc.Size","width":640,"height":480},"_trs":{"__type__":"TypedArray","ctor":"Float64Array","array":[0,-260,0,0,0,0,1,1,1,1]}}],{"__type__":"cc.SpriteFrame","content":{"name":"icon_right","texture":"11a19256c","rect":[3,280,88,91],"offset":[0,0],"originalSize":[88,91],"rotated":1,"capInsets":[0,0,0,0]}},{"__type__":"cc.SpriteFrame","content":{"name":"003a","texture":"e4XtTiNE5OpJfNa+JjR5vJ","rect":[0,0,724,544],"offset":[0,0],"originalSize":[724,544],"capInsets":[0,0,0,0]}},{"__type__":"cc.SpriteFrame","content":{"name":"003b","texture":"68aFxFn6pIPYnZLvI8abqe","rect":[0,0,724,544],"offset":[0,0],"originalSize":[724,544],"capInsets":[0,0,0,0]}}]